batFramework/__init__.py
batFramework/action.py
batFramework/actionContainer.py
batFramework/animatedSprite.py
batFramework/animation.py
batFramework/audioManager.py
batFramework/baseScene.py
batFramework/camera.py
batFramework/constants.py
batFramework/cutscene.py
batFramework/cutsceneManager.py
batFramework/drawable.py
batFramework/dynamicEntity.py
batFramework/easingController.py
batFramework/entity.py
batFramework/enums.py
batFramework/fontManager.py
batFramework/manager.py
batFramework/particle.py
batFramework/propertyEaser.py
batFramework/renderGroup.py
batFramework/resourceManager.py
batFramework/scene.py
batFramework/sceneLayer.py
batFramework/sceneManager.py
batFramework/scrollingSprite.py
batFramework/sprite.py
batFramework/stateMachine.py
batFramework/tileset.py
batFramework/timeManager.py
batFramework/transition.py
batFramework/triggerZone.py
batFramework/utils.py
batFramework/gui/__init__.py
batFramework/gui/animatedLabel.py
batFramework/gui/button.py
batFramework/gui/clickableWidget.py
batFramework/gui/collapseContainer.py
batFramework/gui/container.py
batFramework/gui/debugger.py
batFramework/gui/draggableWidget.py
batFramework/gui/image.py
batFramework/gui/indicator.py
batFramework/gui/interactiveWidget.py
batFramework/gui/label.py
batFramework/gui/layout.py
batFramework/gui/meter.py
batFramework/gui/radioButton.py
batFramework/gui/root.py
batFramework/gui/scrollingContainer.py
batFramework/gui/selector.py
batFramework/gui/shape.py
batFramework/gui/slider.py
batFramework/gui/style.py
batFramework/gui/styleManager.py
batFramework/gui/syncedVar.py
batFramework/gui/textInput.py
batFramework/gui/textWidget.py
batFramework/gui/toggle.py
batFramework/gui/tooltip.py
batFramework/gui/widget.py
batFramework/gui/constraints/__init__.py
batFramework/gui/constraints/constraints.py
batFramework/templates/__init__.py
batFramework/templates/character.py
batFramework/templates/controller.py
batFramework/templates/stateMachine.py
batframework-2.0.1.dist-info/LICENSE
batframework-2.0.1.dist-info/METADATA
batframework-2.0.1.dist-info/WHEEL
batframework-2.0.1.dist-info/top_level.txt
batframework-2.0.1.dist-info/RECORD
