Metadata-Version: 2.2
Name: batframework
Version: 2.0.1
Summary: Pygame framework for making games easier.
Author-email: Turan Baturay <baturayturan@gmail.com>
License: MIT License
Project-URL: Homepage, https://github.com/TuranBaturay/batFramework
Classifier: Programming Language :: Python :: 3
Classifier: License :: OSI Approved :: MIT License
Classifier: Operating System :: OS Independent
Requires-Python: >=3.11
License-File: LICENSE
Requires-Dist: pygame-ce>=2.5.2
